create_gitlab_project/__init__.py
create_gitlab_project/__main__.py
create_gitlab_project/cli.py
create_gitlab_project/constants.py
create_gitlab_project/create_gitlab_project_dfx.py
create_gitlab_project/template/Jenkinsfile
create_gitlab_project/template/README.md
create_jenkins_pipeline/__init__.py
create_jenkins_pipeline/__main__.py
create_jenkins_pipeline/cli.py
create_jenkins_pipeline/constants.py
create_jenkins_pipeline/create_jenkins_pipeline_dfx.py
create_jenkins_pipeline/template/multi_branch.xml
dfx_project_creator-1.0.0.dist-info/METADATA
dfx_project_creator-1.0.0.dist-info/WHEEL
dfx_project_creator-1.0.0.dist-info/top_level.txt
dfx_project_creator-1.0.0.dist-info/RECORD
