Metadata-Version: 2.1
Name: dfx-project-creator
Version: 1.0.0
Summary: Gitlab Project Creation CLI
Home-page: https://teamdefinex.com/
Author: DefineX Labs
Author-email: labs@teamdefinex.com
License: MIT
Keywords: definex gitlab project jenkins job create
Platform: any
Classifier: Programming Language :: Python :: 3
Classifier: License :: OSI Approved :: MIT License
Classifier: Operating System :: OS Independent
Requires-Python: >=3.9
Requires-Dist: python-gitlab (==3.1.0)
Requires-Dist: python-jenkins (==1.7.0)
